renderly/__init__.py
renderly/app.py
renderly/request.py
renderly/response.py
renderly-0.1.4.dist-info/METADATA
renderly-0.1.4.dist-info/WHEEL
renderly-0.1.4.dist-info/top_level.txt
renderly-0.1.4.dist-info/RECORD
