Metadata-Version: 2.4
Name: Renderly
Version: 0.1.4
Summary: Simple Python Web Framework
Requires-Python: >=3.12
Requires-Dist: mako>=1.3.10
Requires-Dist: uwsgi>=2.0.29
